documentation/__init__.py
documentation/conf.py
game2dboard/Board.py
game2dboard/Cell.py
game2dboard/ImageMap.py
game2dboard/OutputBar.py
game2dboard/__init__.py
game2dboard/board.py
game2dboard/cell.py
game2dboard/imagemap.py
game2dboard/outputbar.py
game2dboard-0.9.1.dist-info/LICENSE
game2dboard-0.9.1.dist-info/METADATA
game2dboard-0.9.1.dist-info/WHEEL
game2dboard-0.9.1.dist-info/top_level.txt
game2dboard-0.9.1.dist-info/RECORD
