Metadata-Version: 2.1
Name: game2dboard
Version: 0.9.1
Summary: Python GUI library for creating 2D arrays based board games
Home-page: https://github.com/mjbrusso/game2dboard
Author: Marcos Brusso
Author-email: mjbrusso@gmail.com
License: MIT License
Keywords: GUI,game2dboard,2D,Matrices,array
Platform: UNKNOWN
Classifier: Development Status :: 4 - Beta
Classifier: Programming Language :: Python :: 3
Classifier: Topic :: Education
Classifier: Topic :: Software Development :: User Interfaces
Classifier: Intended Audience :: Education
Classifier: Intended Audience :: Developers
Classifier: License :: OSI Approved :: MIT License
Requires-Python: >=3
